filum_analytics/__init__.py
filum_analytics/client.py
filum_analytics/consumer.py
filum_analytics/request.py
filum_analytics/utils.py
filum_analytics/version.py
filum_analytics_python-1.1.2.dist-info/LICENSE
filum_analytics_python-1.1.2.dist-info/METADATA
filum_analytics_python-1.1.2.dist-info/WHEEL
filum_analytics_python-1.1.2.dist-info/top_level.txt
filum_analytics_python-1.1.2.dist-info/RECORD
