Metadata-Version: 2.1
Name: filum-analytics-python
Version: 1.1.2
Summary: The official Python SDK for Filum BDP
Home-page: https://github.com/Filum-AI/filum-python-sdk
Author: Filum AI
Author-email: hiep@filum.ai
Maintainer: Filum AI
Maintainer-email: hiep@filum.ai
License: MIT License
Platform: UNKNOWN
Classifier: Development Status :: 5 - Production/Stable
Classifier: Intended Audience :: Developers
Classifier: License :: OSI Approved :: MIT License
Classifier: Operating System :: OS Independent
Classifier: Programming Language :: Python
Classifier: Programming Language :: Python :: 2
Classifier: Programming Language :: Python :: 2.6
Classifier: Programming Language :: Python :: 2.7
Classifier: Programming Language :: Python :: 3
Classifier: Programming Language :: Python :: 3.2
Classifier: Programming Language :: Python :: 3.3
Classifier: Programming Language :: Python :: 3.4
Classifier: Programming Language :: Python :: 3.5
Requires-Dist: requests (<3.0,>=2.7)
Requires-Dist: six (>=1.5)
Requires-Dist: monotonic (>=1.5)
Requires-Dist: backoff (==1.6.0)
Requires-Dist: python-dateutil (>2.1)
